benchmarks/__init__.py
benchmarks/datasets.py
benchmarks/metrics.py
benchmarks/run_ablation.py
benchmarks/run_npll_benchmark.py
npll/__init__.py
npll/bootstrap.py
npll/npll_model.py
npll/core/__init__.py
npll/core/knowledge_graph.py
npll/core/logical_rules.py
npll/core/mln.py
npll/inference/__init__.py
npll/inference/e_step.py
npll/inference/elbo.py
npll/inference/m_step.py
npll/scoring/__init__.py
npll/scoring/embeddings.py
npll/scoring/probability.py
npll/scoring/scoring_module.py
npll/training/__init__.py
npll/training/evaluation.py
npll/training/npll_trainer.py
npll/utils/__init__.py
npll/utils/batch_utils.py
npll/utils/config.py
npll/utils/math_utils.py
odin/__init__.py
odin/engine.py
odin_engine-0.1.0.dist-info/licenses/LICENSE
retrieval/__init__.py
retrieval/adapters.py
retrieval/adapters_arango.py
retrieval/aggregators.py
retrieval/beam.py
retrieval/budget.py
retrieval/cache.py
retrieval/confidence.py
retrieval/eval.py
retrieval/linker.py
retrieval/metrics.py
retrieval/metrics_motifs.py
retrieval/orchestrator.py
retrieval/ppr.py
retrieval/ppr_cache.py
retrieval/scoring.py
retrieval/ppr/__init__.py
retrieval/ppr/anchors.py
retrieval/ppr/bippr.py
retrieval/ppr/engines.py
retrieval/ppr/global_pr.py
retrieval/ppr/indexes.py
retrieval/utils/__init__.py
retrieval/utils/pii_redaction.py
retrieval/writers/__init__.py
retrieval/writers/arango_writer.py
retrieval/writers/base.py
retrieval/writers/janus_writer.py
odin_engine-0.1.0.dist-info/METADATA
odin_engine-0.1.0.dist-info/WHEEL
odin_engine-0.1.0.dist-info/top_level.txt
odin_engine-0.1.0.dist-info/RECORD
