Metadata-Version: 2.4
Name: odin-engine
Version: 0.1.0
Summary: Odin: Graph intelligence engine with PPR + NPLL for AI agent navigation
Author: Prescott Data
License: MIT
Project-URL: Homepage, https://bitbucket.org/dromos/odin-kg-engine
Keywords: knowledge-graph,graph-intelligence,pagerank,neural-logic,ai-agents,graph-exploration
Classifier: Development Status :: 4 - Beta
Classifier: Intended Audience :: Developers
Classifier: Intended Audience :: Science/Research
Classifier: License :: OSI Approved :: MIT License
Classifier: Programming Language :: Python :: 3
Classifier: Programming Language :: Python :: 3.9
Classifier: Programming Language :: Python :: 3.10
Classifier: Programming Language :: Python :: 3.11
Classifier: Programming Language :: Python :: 3.12
Classifier: Programming Language :: Python :: 3.13
Classifier: Topic :: Scientific/Engineering :: Artificial Intelligence
Classifier: Topic :: Database
Requires-Python: >=3.9
License-File: LICENSE
Requires-Dist: torch>=2.0.0
Requires-Dist: python-arango>=7.0
Requires-Dist: numpy>=1.20.0
Requires-Dist: networkx>=3.0
Requires-Dist: scipy>=1.10.0
Requires-Dist: scikit-learn>=1.3.0
Requires-Dist: gremlinpython>=3.5.0
Provides-Extra: dev
Requires-Dist: pytest>=7.0; extra == "dev"
Requires-Dist: pytest-cov; extra == "dev"
Requires-Dist: flake8; extra == "dev"
Requires-Dist: bandit; extra == "dev"
Dynamic: license-file
